bjj/__init__.py
bjj/bjj.py
bjj-0.0.1.dist-info/DESCRIPTION.rst
bjj-0.0.1.dist-info/METADATA
bjj-0.0.1.dist-info/RECORD
bjj-0.0.1.dist-info/WHEEL
bjj-0.0.1.dist-info/metadata.json
bjj-0.0.1.dist-info/top_level.txt
