Metadata-Version: 2.0
Name: bjj
Version: 0.0.1
Summary: wu
Home-page: UNKNOWN
Author-email: 525399365@qq.com
License: UNKNOWN
Platform: UNKNOWN
Classifier: Programming Language :: Python :: 3
Classifier: License :: OSI Approved :: MIT License
Classifier: Operating System :: OS Independent
